{
  "generatedAt": "2026-06-21T23:27:43.085Z",
  "mode": "apply",
  "checked": 13,
  "resolved": 0,
  "skipped": 13,
  "ok": true,
  "error": "",
  "games": [
    {
      "gameId": "world_cup_26",
      "gameTitle": "World Cup 26",
      "checked": 13,
      "resolved": 0,
      "skipped": 13,
      "events": [
        {
          "type": "skipped",
          "gameId": "world_cup_26",
          "gameTitle": "World Cup 26",
          "gwId": "GW6",
          "email": "tdraynor@gmail.com",
          "pick": "England",
          "reason": "Fixture unresolved",
          "fixture": "Panama v England"
        },
        {
          "type": "skipped",
          "gameId": "world_cup_26",
          "gameTitle": "World Cup 26",
          "gwId": "GW6",
          "email": "ciarananthonykelly@gmail.com",
          "pick": "England",
          "reason": "Fixture unresolved",
          "fixture": "Panama v England"
        },
        {
          "type": "skipped",
          "gameId": "world_cup_26",
          "gameTitle": "World Cup 26",
          "gwId": "GW6",
          "email": "patrickdeclankelly@gmail.com",
          "pick": "England",
          "reason": "Fixture unresolved",
          "fixture": "Panama v England"
        },
        {
          "type": "skipped",
          "gameId": "world_cup_26",
          "gameTitle": "World Cup 26",
          "gwId": "GW4",
          "email": "ciarananthonykelly@gmail.com",
          "pick": "France",
          "reason": "Fixture unresolved",
          "fixture": "France v Iraq"
        },
        {
          "type": "skipped",
          "gameId": "world_cup_26",
          "gameTitle": "World Cup 26",
          "gwId": "GW4",
          "email": "patrickdeclankelly@gmail.com",
          "pick": "France",
          "reason": "Fixture unresolved",
          "fixture": "France v Iraq"
        },
        {
          "type": "skipped",
          "gameId": "world_cup_26",
          "gameTitle": "World Cup 26",
          "gwId": "GW4",
          "email": "adam.drysdale@hotmail.com",
          "pick": "France",
          "reason": "Fixture unresolved",
          "fixture": "France v Iraq"
        },
        {
          "type": "skipped",
          "gameId": "world_cup_26",
          "gameTitle": "World Cup 26",
          "gwId": "GW4",
          "email": "barnabysargent@gmail.com",
          "pick": "Croatia",
          "reason": "Fixture unresolved",
          "fixture": "Panama v Croatia"
        },
        {
          "type": "skipped",
          "gameId": "world_cup_26",
          "gameTitle": "World Cup 26",
          "gwId": "GW4",
          "email": "peleschkaewan12@gmail.com",
          "pick": "Egypt",
          "reason": "Fixture unresolved",
          "fixture": "New Zealand v Egypt"
        },
        {
          "type": "skipped",
          "gameId": "world_cup_26",
          "gameTitle": "World Cup 26",
          "gwId": "GW4",
          "email": "adam@tatatastudios.com",
          "pick": "France",
          "reason": "Fixture unresolved",
          "fixture": "France v Iraq"
        },
        {
          "type": "skipped",
          "gameId": "world_cup_26",
          "gameTitle": "World Cup 26",
          "gwId": "GW4",
          "email": "tdraynor@gmail.com",
          "pick": "France",
          "reason": "Fixture unresolved",
          "fixture": "France v Iraq"
        },
        {
          "type": "skipped",
          "gameId": "world_cup_26",
          "gameTitle": "World Cup 26",
          "gwId": "GW5",
          "email": "ciarananthonykelly@gmail.com",
          "pick": "Morocco",
          "reason": "Fixture unresolved",
          "fixture": "Morocco v Haiti"
        },
        {
          "type": "skipped",
          "gameId": "world_cup_26",
          "gameTitle": "World Cup 26",
          "gwId": "GW5",
          "email": "patrickdeclankelly@gmail.com",
          "pick": "Ivory Coast",
          "reason": "Fixture unresolved",
          "fixture": "Curacao v Ivory Coast"
        },
        {
          "type": "skipped",
          "gameId": "world_cup_26",
          "gameTitle": "World Cup 26",
          "gwId": "GW5",
          "email": "tdraynor@gmail.com",
          "pick": "Germany",
          "reason": "Fixture unresolved",
          "fixture": "Ecuador v Germany"
        },
        {
          "type": "queue-recalc",
          "gameId": "world_cup_26",
          "gameTitle": "World Cup 26",
          "reason": "Recalculated Firebase queued/pending/void picks",
          "changed": 0,
          "checked": 225,
          "ok": true
        },
        {
          "type": "registration-recalc",
          "gameId": "world_cup_26",
          "gameTitle": "World Cup 26",
          "reason": "Recalculated Firebase alive/dead registrations",
          "changed": 0,
          "checked": 61,
          "ok": true
        },
        {
          "type": "sheets-sync",
          "gameId": "world_cup_26",
          "gameTitle": "World Cup 26",
          "reason": "Synced Sheets picks from Firebase",
          "changed": 225,
          "checked": 225,
          "ok": true
        }
      ]
    },
    {
      "gameId": "the_run_in",
      "gameTitle": "The Run In",
      "checked": 0,
      "resolved": 0,
      "skipped": 0,
      "events": []
    },
    {
      "gameId": "spring_2026_lms",
      "gameTitle": "Spring 2026 LMS",
      "checked": 0,
      "resolved": 0,
      "skipped": 0,
      "events": []
    },
    {
      "gameId": "jan_2026_lms",
      "gameTitle": "January 2026 LMS",
      "checked": 0,
      "resolved": 0,
      "skipped": 0,
      "events": []
    }
  ]
}
